solow_library/__init__.py
solow_library/solow.py
solow_library/user_interface.py
solow_sim-0.1.3.dist-info/METADATA
solow_sim-0.1.3.dist-info/WHEEL
solow_sim-0.1.3.dist-info/top_level.txt
solow_sim-0.1.3.dist-info/RECORD
